reelscraper/__init__.py
reelscraper/reel_multi_scraper.py
reelscraper/reel_scraper.py
reelscraper/utils/__init__.py
reelscraper/utils/account_manager.py
reelscraper/utils/extractor.py
reelscraper/utils/instagram_api.py
reelscraper/utils/logger_manager.py
reelscraper/utils/database/__init__.py
reelscraper/utils/database/db_base.py
reelscraper/utils/database/db_manager.py
reelscraper-2.2.2.dist-info/LICENSE.txt
reelscraper-2.2.2.dist-info/METADATA
reelscraper-2.2.2.dist-info/WHEEL
reelscraper-2.2.2.dist-info/entry_points.txt
reelscraper-2.2.2.dist-info/top_level.txt
reelscraper-2.2.2.dist-info/RECORD
