Metadata-Version: 2.2
Name: reelscraper
Version: 2.2.2
Summary: A convenient way to harvest Reels data without breaking a sweat—or Instagram's TOS
Author-email: Andrea Zorzi <zorzi.andrea@outlook.com>
License: LICENSE.txt
Project-URL: Home, https://github.com/andreaaazo/reelscraper
Project-URL: Bug Tracker, https://github.com/andreaaazo/reelscraper/issues
Project-URL: Documentation, https://github.com/andreaaazo/reelscraper/blob/master/DOCS.md
Keywords: instagram,scraper,reels
Classifier: Development Status :: 3 - Alpha
Classifier: Environment :: Console
Classifier: Intended Audience :: Developers
Classifier: Programming Language :: Python :: 3
Classifier: Operating System :: OS Independent
Classifier: License :: OSI Approved :: MIT License
Requires-Python: >=3.9
License-File: LICENSE.txt
Requires-Dist: certifi==2024.12.14
Requires-Dist: charset-normalizer==3.4.1
Requires-Dist: et_xmlfile==2.0.0
Requires-Dist: fake-useragent==2.0.3
Requires-Dist: idna==3.10
Requires-Dist: openpyxl==3.1.5
Requires-Dist: PyYAML==6.0.2
Requires-Dist: requests==2.32.3
Requires-Dist: urllib3==2.3.0
Requires-Dist: SQLAlchemy==2.0.37
